url_counter/__init__.py
url_counter/main.py
Api_Counter-2.2.3.dist-info/METADATA
Api_Counter-2.2.3.dist-info/WHEEL
Api_Counter-2.2.3.dist-info/entry_points.txt
Api_Counter-2.2.3.dist-info/top_level.txt
Api_Counter-2.2.3.dist-info/RECORD
