Metadata-Version: 2.1
Name: Api-Counter
Version: 2.2.3
Summary: Simple API Counter from log files or folder.
Home-page: https://github.com/windies21/api-counter
Author: winDy
Author-email: winDy@windystudio.com
License: MIT
Requires-Python: >=3.11.0
Requires-Dist: Yirgachefe
Requires-Dist: click
Requires-Dist: rich
Requires-Dist: pytest
Provides-Extra: dev
Requires-Dist: pytest ; extra == 'dev'
Requires-Dist: flake8 ; extra == 'dev'
Requires-Dist: flake8-docstrings ; extra == 'dev'
Requires-Dist: black ; extra == 'dev'
Requires-Dist: isort ; extra == 'dev'
Provides-Extra: lint
Requires-Dist: flake8 ; extra == 'lint'
Requires-Dist: flake8-docstrings ; extra == 'lint'
Provides-Extra: tests
Requires-Dist: pytest ; extra == 'tests'
